{
    "quizTopic": "General Knowledge",
    "title": "99% People Fail This Quiz 😱 Can You Get 5/5?",
    "description": "Test your brain in 5 seconds per question ⏳ Comment your score below 👇 #gk #quiz #shorts #challenge",
    "questions": [
        {
            "question": "किस जानवर का दूध गुलाबी रंग का होता है?",
            "options": {
                "A": "दरियाई घोड़ा",
                "B": "ऊँट",
                "C": "जिराफ",
                "D": "बंदर"
            },
            "correctAnswer": "A"
        },
        {
            "question": "शरीर के किस अंग में रक्त नहीं पाया जाता है?",
            "options": {
                "A": "नाखून",
                "B": "कॉर्निया",
                "C": "बाल",
                "D": "कान"
            },
            "correctAnswer": "B"
        },
        {
            "question": "शांति का प्रतीक किस पक्षी को माना जाता है?",
            "options": {
                "A": "मोर",
                "B": "हंस",
                "C": "कबूतर",
                "D": "कोयल"
            },
            "correctAnswer": "C"
        },
        {
            "question": "किस ग्रह को 'भोर का तारा' कहा जाता है?",
            "options": {
                "A": "मंगल",
                "B": "शनि",
                "C": "शुक्र",
                "D": "बुध"
            },
            "correctAnswer": "C"
        },
        {
            "question": "किस देश में एक भी मच्छर नहीं पाया जाता है?",
            "options": {
                "A": "फ्रांस",
                "B": "आइसलैंड",
                "C": "जापान",
                "D": "कनाडा"
            },
            "correctAnswer": "B"
        }
    ]
}